LICENSE
README.md
setup.py
fincalc/__init__.py
fincalc/helper.py
fincalc.egg-info/PKG-INFO
fincalc.egg-info/SOURCES.txt
fincalc.egg-info/dependency_links.txt
fincalc.egg-info/top_level.txt