Metadata-Version: 2.1
Name: fincalc
Version: 1.1.0
Summary: A Financial Calculator
Home-page: https://github.com/mahyar-amiri/fincalc
Author: Mahyar Amiri
Author-email: mmaahhyyaarr@gmail.com
License: MIT
Classifier: Programming Language :: Python :: 3
Classifier: License :: OSI Approved :: MIT License
Classifier: Operating System :: OS Independent
Requires-Python: >=3.6
License-File: LICENSE
